{
  "generated_utc": "2026-07-04T01:49:33.640526Z",
  "leaderboard": [
    {
      "name": "Luke Clark",
      "grp": 4700,
      "correct": 47,
      "graded": 72,
      "ko": 1300,
      "rounds": {
        "R32": 1300,
        "R16": 0,
        "QF": 0,
        "SF": 0,
        "Final": 0
      },
      "total": 6000,
      "baseline": 0,
      "ko_only": false,
      "champ": "France",
      "final_goals_guess": null,
      "rank": 1,
      "move": 0
    },
    {
      "name": "Ryan Sheekley",
      "grp": 4600,
      "correct": 46,
      "graded": 72,
      "ko": 1300,
      "rounds": {
        "R32": 1300,
        "R16": 0,
        "QF": 0,
        "SF": 0,
        "Final": 0
      },
      "total": 5900,
      "baseline": 0,
      "ko_only": false,
      "champ": "France",
      "final_goals_guess": null,
      "rank": 2,
      "move": 0
    },
    {
      "name": "Kyle Williams",
      "grp": 4900,
      "correct": 49,
      "graded": 72,
      "ko": 800,
      "rounds": {
        "R32": 800,
        "R16": 0,
        "QF": 0,
        "SF": 0,
        "Final": 0
      },
      "total": 5700,
      "baseline": 0,
      "ko_only": false,
      "champ": "Argentina",
      "final_goals_guess": null,
      "rank": 3,
      "move": 0
    },
    {
      "name": "Andrew Fahey",
      "grp": 4500,
      "correct": 45,
      "graded": 72,
      "ko": 1200,
      "rounds": {
        "R32": 1200,
        "R16": 0,
        "QF": 0,
        "SF": 0,
        "Final": 0
      },
      "total": 5700,
      "baseline": 0,
      "ko_only": false,
      "champ": "Netherlands",
      "final_goals_guess": null,
      "rank": 3,
      "move": 0
    },
    {
      "name": "John Pappas",
      "grp": 4500,
      "correct": 45,
      "graded": 72,
      "ko": 1200,
      "rounds": {
        "R32": 1200,
        "R16": 0,
        "QF": 0,
        "SF": 0,
        "Final": 0
      },
      "total": 5700,
      "baseline": 0,
      "ko_only": false,
      "champ": "France",
      "final_goals_guess": null,
      "rank": 3,
      "move": 0
    },
    {
      "name": "Karlis Draulis",
      "grp": 4400,
      "correct": 44,
      "graded": 72,
      "ko": 1100,
      "rounds": {
        "R32": 1100,
        "R16": 0,
        "QF": 0,
        "SF": 0,
        "Final": 0
      },
      "total": 5500,
      "baseline": 0,
      "ko_only": false,
      "champ": "France",
      "final_goals_guess": null,
      "rank": 6,
      "move": 0
    },
    {
      "name": "Keegan Ball",
      "grp": 4300,
      "correct": 43,
      "graded": 72,
      "ko": 1200,
      "rounds": {
        "R32": 1200,
        "R16": 0,
        "QF": 0,
        "SF": 0,
        "Final": 0
      },
      "total": 5500,
      "baseline": 0,
      "ko_only": false,
      "champ": "England",
      "final_goals_guess": null,
      "rank": 6,
      "move": 0
    },
    {
      "name": "Brad Bone",
      "grp": 4200,
      "correct": 42,
      "graded": 72,
      "ko": 1300,
      "rounds": {
        "R32": 1300,
        "R16": 0,
        "QF": 0,
        "SF": 0,
        "Final": 0
      },
      "total": 5500,
      "baseline": 0,
      "ko_only": false,
      "champ": "France",
      "final_goals_guess": null,
      "rank": 6,
      "move": 0
    },
    {
      "name": "John Atkins",
      "grp": 3800,
      "correct": 0,
      "graded": 72,
      "ko": 1100,
      "rounds": {
        "R32": 1100,
        "R16": 0,
        "QF": 0,
        "SF": 0,
        "Final": 0
      },
      "total": 4900,
      "baseline": 3800,
      "ko_only": true,
      "champ": "France",
      "final_goals_guess": null,
      "rank": 9,
      "move": 0
    }
  ]
}